setup.py
approxeng.hwsupport.egg-info/PKG-INFO
approxeng.hwsupport.egg-info/SOURCES.txt
approxeng.hwsupport.egg-info/dependency_links.txt
approxeng.hwsupport.egg-info/requires.txt
approxeng.hwsupport.egg-info/top_level.txt
approxeng/hwsupport/__init__.py
approxeng/hwsupport/adcs.py
approxeng/hwsupport/css4_colours.py
approxeng/hwsupport/gui.py
approxeng/hwsupport/leds.py
approxeng/hwsupport/motors.py
approxeng/hwsupport/servos.py
approxeng/hwsupport/util.py