Metadata-Version: 1.1
Name: approxeng.hwsupport
Version: 0.1.2
Summary: Python robot hardware driver support
Home-page: https://github.com/ApproxEng/approxeng.hwsupport
Author: Tom Oinn
Author-email: tomoinn@gmail.com
License: UNKNOWN
Platform: UNKNOWN
Classifier: Programming Language :: Python :: 3.6
